{
  "exclude_rules": [],
  "generated_at": "2026-03-15T11:50:26.958157+00:00",
  "include_rules": [],
  "outcomes": [
    {
      "error": null,
      "explained_at": "2026-03-15T11:50:26.932432+00:00",
      "explanation_kind": "pass_through",
      "explanation_summary": "Accepted because no include allowlist is configured and no exclude rules matched.",
      "full_name": "xigh/herbert-rs",
      "github_repository_id": 1182247216,
      "matched_exclude_rules": [],
      "matched_include_rules": [],
      "queue_status": "completed",
      "triage_status": "accepted"
    },
    {
      "error": null,
      "explained_at": "2026-03-15T11:50:26.934608+00:00",
      "explanation_kind": "pass_through",
      "explanation_summary": "Accepted because no include allowlist is configured and no exclude rules matched.",
      "full_name": "Cyber-Hive-Security/ion-drift",
      "github_repository_id": 1181380664,
      "matched_exclude_rules": [],
      "matched_include_rules": [],
      "queue_status": "completed",
      "triage_status": "accepted"
    },
    {
      "error": null,
      "explained_at": "2026-03-15T11:50:26.936173+00:00",
      "explanation_kind": "pass_through",
      "explanation_summary": "Accepted because no include allowlist is configured and no exclude rules matched.",
      "full_name": "bopalvelut-prog/autoresearch",
      "github_repository_id": 1181659917,
      "matched_exclude_rules": [],
      "matched_include_rules": [],
      "queue_status": "completed",
      "triage_status": "accepted"
    },
    {
      "error": null,
      "explained_at": "2026-03-15T11:50:26.938091+00:00",
      "explanation_kind": "pass_through",
      "explanation_summary": "Accepted because no include allowlist is configured and no exclude rules matched.",
      "full_name": "qiu7824/zsclip",
      "github_repository_id": 1181704979,
      "matched_exclude_rules": [],
      "matched_include_rules": [],
      "queue_status": "completed",
      "triage_status": "accepted"
    },
    {
      "error": null,
      "explained_at": "2026-03-15T11:50:26.939801+00:00",
      "explanation_kind": "pass_through",
      "explanation_summary": "Accepted because no include allowlist is configured and no exclude rules matched.",
      "full_name": "clifforj/gbs-master",
      "github_repository_id": 1181818704,
      "matched_exclude_rules": [],
      "matched_include_rules": [],
      "queue_status": "completed",
      "triage_status": "accepted"
    },
    {
      "error": null,
      "explained_at": "2026-03-15T11:50:26.941288+00:00",
      "explanation_kind": "pass_through",
      "explanation_summary": "Accepted because no include allowlist is configured and no exclude rules matched.",
      "full_name": "XingYujieee/GPTicker",
      "github_repository_id": 1181830460,
      "matched_exclude_rules": [],
      "matched_include_rules": [],
      "queue_status": "completed",
      "triage_status": "accepted"
    },
    {
      "error": null,
      "explained_at": "2026-03-15T11:50:26.942902+00:00",
      "explanation_kind": "pass_through",
      "explanation_summary": "Accepted because no include allowlist is configured and no exclude rules matched.",
      "full_name": "ahmadmayahi/clean-code-in-laravel",
      "github_repository_id": 1181886181,
      "matched_exclude_rules": [],
      "matched_include_rules": [],
      "queue_status": "completed",
      "triage_status": "accepted"
    },
    {
      "error": null,
      "explained_at": "2026-03-15T11:50:26.944565+00:00",
      "explanation_kind": "pass_through",
      "explanation_summary": "Accepted because no include allowlist is configured and no exclude rules matched.",
      "full_name": "nanostores/async",
      "github_repository_id": 1181946259,
      "matched_exclude_rules": [],
      "matched_include_rules": [],
      "queue_status": "completed",
      "triage_status": "accepted"
    },
    {
      "error": null,
      "explained_at": "2026-03-15T11:50:26.946291+00:00",
      "explanation_kind": "pass_through",
      "explanation_summary": "Accepted because no include allowlist is configured and no exclude rules matched.",
      "full_name": "apo-bozdag/SoundShift",
      "github_repository_id": 1181962187,
      "matched_exclude_rules": [],
      "matched_include_rules": [],
      "queue_status": "completed",
      "triage_status": "accepted"
    },
    {
      "error": null,
      "explained_at": "2026-03-15T11:50:26.947969+00:00",
      "explanation_kind": "pass_through",
      "explanation_summary": "Accepted because no include allowlist is configured and no exclude rules matched.",
      "full_name": "simranjeet97/SelfExtendingAgent_ADKGoogle",
      "github_repository_id": 1181963628,
      "matched_exclude_rules": [],
      "matched_include_rules": [],
      "queue_status": "completed",
      "triage_status": "accepted"
    },
    {
      "error": null,
      "explained_at": "2026-03-15T11:50:26.949521+00:00",
      "explanation_kind": "pass_through",
      "explanation_summary": "Accepted because no include allowlist is configured and no exclude rules matched.",
      "full_name": "Lethe044/hermes-life-os",
      "github_repository_id": 1181994538,
      "matched_exclude_rules": [],
      "matched_include_rules": [],
      "queue_status": "completed",
      "triage_status": "accepted"
    },
    {
      "error": null,
      "explained_at": "2026-03-15T11:50:26.951058+00:00",
      "explanation_kind": "pass_through",
      "explanation_summary": "Accepted because no include allowlist is configured and no exclude rules matched.",
      "full_name": "juraijmughal378-png/Cyberster-Red-Team-Internship-Week-02-Network-Enumeration-Service-Vulnerability-Discovery",
      "github_repository_id": 1182004104,
      "matched_exclude_rules": [],
      "matched_include_rules": [],
      "queue_status": "completed",
      "triage_status": "accepted"
    },
    {
      "error": null,
      "explained_at": "2026-03-15T11:50:26.952578+00:00",
      "explanation_kind": "pass_through",
      "explanation_summary": "Accepted because no include allowlist is configured and no exclude rules matched.",
      "full_name": "Abzaek/chat-exporter",
      "github_repository_id": 1182225068,
      "matched_exclude_rules": [],
      "matched_include_rules": [],
      "queue_status": "completed",
      "triage_status": "accepted"
    },
    {
      "error": null,
      "explained_at": "2026-03-15T11:50:26.954084+00:00",
      "explanation_kind": "pass_through",
      "explanation_summary": "Accepted because no include allowlist is configured and no exclude rules matched.",
      "full_name": "Guoziiimakabaka/arxivdailypullagent",
      "github_repository_id": 1182239734,
      "matched_exclude_rules": [],
      "matched_include_rules": [],
      "queue_status": "completed",
      "triage_status": "accepted"
    },
    {
      "error": null,
      "explained_at": "2026-03-15T11:50:26.955560+00:00",
      "explanation_kind": "pass_through",
      "explanation_summary": "Accepted because no include allowlist is configured and no exclude rules matched.",
      "full_name": "jbobbink/firehose-daily-seo-checks",
      "github_repository_id": 1182248165,
      "matched_exclude_rules": [],
      "matched_include_rules": [],
      "queue_status": "completed",
      "triage_status": "accepted"
    },
    {
      "error": null,
      "explained_at": "2026-03-15T11:50:26.957118+00:00",
      "explanation_kind": "pass_through",
      "explanation_summary": "Accepted because no include allowlist is configured and no exclude rules matched.",
      "full_name": "Ichihiroy/ghelper-for-linux",
      "github_repository_id": 1182301906,
      "matched_exclude_rules": [],
      "matched_include_rules": [],
      "queue_status": "completed",
      "triage_status": "accepted"
    }
  ],
  "status": "success",
  "summary": {
    "accepted": 16,
    "failed": 0,
    "rejected": 0
  }
}
